anydi_django/__init__.py
anydi_django/_container.py
anydi_django/_settings.py
anydi_django/_utils.py
anydi_django/apps.py
anydi_django/middleware.py
anydi_django/ninja/__init__.py
anydi_django/ninja/_operation.py
anydi_django/ninja/_signature.py
anydi_django-0.5.0.dist-info/WHEEL
anydi_django-0.5.0.dist-info/METADATA
anydi_django-0.5.0.dist-info/RECORD
