Metadata-Version: 2.3
Name: anydi-django
Version: 0.5.0
Summary: Add your description here
Requires-Dist: anydi>=0.62.0
Requires-Dist: django>=4.2
Requires-Dist: django-ninja>=1.1.0,<2 ; extra == 'ninja'
Requires-Python: >=3.10
Provides-Extra: ninja
